ansible/module_utils/dynload/__init__.py
klarrio_ansible-0.3.0.dist-info/METADATA
klarrio_ansible-0.3.0.dist-info/RECORD
klarrio_ansible-0.3.0.dist-info/WHEEL
klarrio_ansible-0.3.0.dist-info/top_level.txt
